.travis.yml
CHANGES.rst
CONTRIBUTORS.rst
MANIFEST.in
Makefile
README.rst
bootstrap.py
buildout.cfg
setup.py
docs/LICENSE.GPL
docs/LICENSE.txt
local/.travis.yml
local/Makefile
local/README.rst
local/bootstrap.py
local/buildout.cfg
local/setup.py
local/docs/LICENSE.GPL
local/docs/LICENSE.txt
local/plonesocial/__init__.py
local/plonesocial/activitystream/__init__.py
local/plonesocial/activitystream/adapters.py
local/plonesocial/activitystream/configure.zcml
local/plonesocial/activitystream/integration.py
local/plonesocial/activitystream/interfaces.py
local/plonesocial/activitystream/synci18n.sh
local/plonesocial/activitystream/testing.py
local/plonesocial/activitystream/Extensions/Install.py
local/plonesocial/activitystream/Extensions/__init__.py
local/plonesocial/activitystream/browser/__init__.py
local/plonesocial/activitystream/browser/activity_provider.py
local/plonesocial/activitystream/browser/activitystream_portal.py
local/plonesocial/activitystream/browser/activitystream_portal.zcml
local/plonesocial/activitystream/browser/configure.zcml
local/plonesocial/activitystream/browser/interfaces.py
local/plonesocial/activitystream/browser/navigation.py
local/plonesocial/activitystream/browser/stream.py
local/plonesocial/activitystream/browser/stream_provider.py
local/plonesocial/activitystream/browser/stylesheets/activitystream.css
local/plonesocial/activitystream/browser/templates/activity_provider.pt
local/plonesocial/activitystream/browser/templates/activitystream_portal.pt
local/plonesocial/activitystream/browser/templates/activitystream_portlet.pt
local/plonesocial/activitystream/browser/templates/activitystream_portletmanager_view.pt
local/plonesocial/activitystream/browser/templates/activitystream_portletmanager_viewlet.pt
local/plonesocial/activitystream/browser/templates/navigation.pt
local/plonesocial/activitystream/browser/templates/stream.pt
local/plonesocial/activitystream/browser/templates/stream_provider.pt
plonesocial.activitystream.egg-info/PKG-INFO
plonesocial.activitystream.egg-info/SOURCES.txt
plonesocial.activitystream.egg-info/dependency_links.txt
plonesocial.activitystream.egg-info/entry_points.txt
plonesocial.activitystream.egg-info/namespace_packages.txt
plonesocial.activitystream.egg-info/not-zip-safe
plonesocial.activitystream.egg-info/requires.txt
plonesocial.activitystream.egg-info/top_level.txt
