Metadata-Version: 1.1
Name: plonesocial.activitystream
Version: 0.5.6
Summary: This package provides views for plonesocial.microblog status updates and other user activities in Plone
Home-page: http://github.com/cosent/plonesocial.activitystream
Author: Guido Stevens
Author-email: guido.stevens@cosent.net
License: UNKNOWN
Keywords: plone socbiz social microblog activity stream
Platform: UNKNOWN
Classifier: Development Status :: 3 - Alpha
Classifier: Environment :: Web Environment
Classifier: Framework :: Plone :: 4.2
Classifier: Framework :: Plone :: 4.3
Classifier: Framework :: Plone
Classifier: License :: OSI Approved :: GNU General Public License v2 (GPLv2)
Classifier: Operating System :: OS Independent
Classifier: Programming Language :: Python :: 2.6
Classifier: Programming Language :: Python :: 2.7
Classifier: Programming Language :: Python
Classifier: Topic :: Software Development :: Libraries :: Python Modules
